1.8.0_181
Classfile /C:/Users/16678596/IdeaProjects/jmeetup/kotlin-bytecode/target/classes/com/github/mrzo0m/HelloKt.class
  Last modified 08.11.2018; size 1015 bytes
  MD5 checksum 7b50efa35b970296ac2b8ed5f2db57f0
  Compiled from "Hello.kt"
public final class com.github.mrzo0m.HelloKt
  minor version: 0
  major version: 50
  flags: ACC_PUBLIC, ACC_FINAL, ACC_SUPER
Constant pool:
   #1 = Utf8               com/github/mrzo0m/HelloKt
   #2 = Class              #1             // com/github/mrzo0m/HelloKt
   #3 = Utf8               java/lang/Object
   #4 = Class              #3             // java/lang/Object
   #5 = Utf8               main
   #6 = Utf8               ([Ljava/lang/String;)V
   #7 = Utf8               Lorg/jetbrains/annotations/NotNull;
   #8 = Utf8               args
   #9 = String             #8             // args
  #10 = Utf8               kotlin/jvm/internal/Intrinsics
  #11 = Class              #10            // kotlin/jvm/internal/Intrinsics
  #12 = Utf8               checkParameterIsNotNull
  #13 = Utf8               (Ljava/lang/Object;Ljava/lang/String;)V
  #14 = NameAndType        #12:#13        // checkParameterIsNotNull:(Ljava/lang/Object;Ljava/lang/String;)V
  #15 = Methodref          #11.#14        // kotlin/jvm/internal/Intrinsics.checkParameterIsNotNull:(Ljava/lang/Object;Ljava/lang/String;)V
  #16 = Utf8               Hello, world!
  #17 = String             #16            // Hello, world!
  #18 = Utf8               java/lang/System
  #19 = Class              #18            // java/lang/System
  #20 = Utf8               out
  #21 = Utf8               Ljava/io/PrintStream;
  #22 = NameAndType        #20:#21        // out:Ljava/io/PrintStream;
  #23 = Fieldref           #19.#22        // java/lang/System.out:Ljava/io/PrintStream;
  #24 = Utf8               java/io/PrintStream
  #25 = Class              #24            // java/io/PrintStream
  #26 = Utf8               println
  #27 = Utf8               (Ljava/lang/Object;)V
  #28 = NameAndType        #26:#27        // println:(Ljava/lang/Object;)V
  #29 = Methodref          #25.#28        // java/io/PrintStream.println:(Ljava/lang/Object;)V
  #30 = Utf8               [Ljava/lang/String;
  #31 = Utf8               Lkotlin/Metadata;
  #32 = Utf8               mv
  #33 = Integer            1
  #34 = Utf8               bv
  #35 = Integer            0
  #36 = Utf8               k
  #37 = Integer            2
  #38 = Utf8               d1
  #39 = Utf8                \n \n\n \n\n\n 0200??
  #40 = Utf8               d2
  #41 = Utf8
  #42 = Utf8               kotlin-bytecode
  #43 = Utf8               Hello.kt
  #44 = Utf8               Code
  #45 = Utf8               LocalVariableTable
  #46 = Utf8               LineNumberTable
  #47 = Utf8               RuntimeInvisibleParameterAnnotations
  #48 = Utf8               SourceFile
  #49 = Utf8               SourceDebugExtension
  #50 = Utf8               RuntimeVisibleAnnotations
{
  public static final void main(java.lang.String[]);
    descriptor: ([Ljava/lang/String;)V
    flags: ACC_PUBLIC, ACC_STATIC, ACC_FINAL
    Code:
      stack=2, locals=2, args_size=1
         0: aload_0
         1: ldc           #9                  // String args
         3: invokestatic  #15                 // Method kotlin/jvm/internal/Intrinsics.checkParameterIsNotNull:(Ljava/lang/Object;Ljava/lang/String;)V
         6: ldc           #17                 // String Hello, world!
         8: astore_1
         9: nop
        10: getstatic     #23                 // Field java/lang/System.out:Ljava/io/PrintStream;
        13: aload_1
        14: invokevirtual #29                 // Method java/io/PrintStream.println:(Ljava/lang/Object;)V
        17: return
      LocalVariableTable:
        Start  Length  Slot  Name   Signature
            0      18     0  args   [Ljava/lang/String;
      LineNumberTable:
        line 4: 6
        line 5: 17
    RuntimeInvisibleParameterAnnotations:
      0:
        0: #7()
}
SourceFile: "Hello.kt"
SourceDebugExtension:
  SMAP
  Hello.kt
  Kotlin
  *S Kotlin
  *F
  + 1 Hello.kt
  com/github/mrzo0m/HelloKt
  *L
  1#1,5:1
  *E
RuntimeVisibleAnnotations:
  0: #31(#32=[I#33,I#33,I#33],#34=[I#33,I#35,I#35],#36=I#37,#38=[s#39],#40=[s#5,s#41,s#8,s#41,s#41,s#6,s#42])
